{
  "session_id": "d76059f7",
  "timestamp": "2026-01-07T06:21:52.746817+00:00",
  "events_analyzed": 100,
  "highlights": [
    "Analyzed 100 events in this session.",
    "Most common event types: PATTERN_RECURRING (29), SYSTEM_SNAPSHOT (16), TREND_DETECTED (12)",
    "Active components: temporal_analyzer, sys_telemetry, reflector_agent, advisor_agent, service_runner",
    "Events span 4.6 hours."
  ],
  "anomalies": [],
  "changes": [],
  "questions": [],
  "suggested_next_steps": [
    "ADVISORY: System appears stable. Continue monitoring."
  ],
  "reflector_role": "reflector_agent",
  "advisory_only": true
}