{
  "session_id": "5a3064d4",
  "timestamp": "2026-01-07T22:01:15.150145+00:00",
  "events_analyzed": 100,
  "highlights": [
    "Analyzed 100 events in this session.",
    "Most common event types: SYSTEM_SNAPSHOT (26), PATTERN_RECURRING (24), SCHEDULED_SNAPSHOT (23)",
    "Active components: temporal_analyzer, scheduled_research, sys_telemetry, intent_manager, advisor_agent",
    "Events span 12.4 hours."
  ],
  "anomalies": [
    {
      "type": "EVENT_GAPS",
      "severity": "info",
      "description": "Found 1 gaps >1 hour in event timeline",
      "max_gap_hours": 5.6
    }
  ],
  "changes": [],
  "questions": [
    "Why were there gaps up to 5.6 hours? Was the system offline?"
  ],
  "suggested_next_steps": [
    "ADVISORY: System appears stable. Continue monitoring."
  ],
  "reflector_role": "reflector_agent",
  "advisory_only": true
}